lazylines/__init__.py
lazylines/functions.py
lazylines-0.1.0.dist-info/licenses/LICENSE
lazylines-0.1.0.dist-info/METADATA
lazylines-0.1.0.dist-info/WHEEL
lazylines-0.1.0.dist-info/top_level.txt
lazylines-0.1.0.dist-info/RECORD
