Metadata-Version: 2.4
Name: lazylines
Version: 0.1.0
Summary: A lazy way to process lines from files
Author: Vincent D. Warmerdam
License: MIT
Classifier: Intended Audience :: Science/Research
Classifier: Programming Language :: Python :: 3
Classifier: Programming Language :: Python :: 3.8
Classifier: Programming Language :: Python :: 3.9
Classifier: Programming Language :: Python :: 3.10
Classifier: Programming Language :: Python :: 3.11
Classifier: Programming Language :: Python :: 3.12
Classifier: License :: OSI Approved :: MIT License
Requires-Python: >=3.8
License-File: LICENSE
Requires-Dist: srsly>=2.0.8
Requires-Dist: tqdm>=4.64.1
Requires-Dist: pydantic>=2.0.0
Provides-Extra: dev
Requires-Dist: pytest>=5.4.3; extra == "dev"
Requires-Dist: mktestdocs>=0.1.0; extra == "dev"
Requires-Dist: interrogate>=1.2.0; extra == "dev"
Requires-Dist: mkdocs-material; extra == "dev"
Requires-Dist: mkdocstrings-python; extra == "dev"
Requires-Dist: ruff>=0.1.0; extra == "dev"
Requires-Dist: pre-commit>=3.0.0; extra == "dev"
Dynamic: license-file
